bioumlsim/__init__.py
bioumlsim/jdkhandler.py
bioumlsim/model.py
bioumlsim/test.py
bioumlsim/test.xml
bioumlsim/jars/biouml.plugins.sbml_0.9.10.jar
bioumlsim/jars/biouml.plugins.simulation_0.9.10.jar
bioumlsim/jars/biouml.workbench_0.9.10.jar
bioumlsim/jars/colt.jar
bioumlsim/jars/com.developmentontheedge.beans-3.0.4.jar
bioumlsim/jars/com.developmentontheedge.util_0.9.10.jar
bioumlsim/jars/com.eclipsesource.json_0.9.4.jar
bioumlsim/jars/org.apache.commons.collections_3.2.1.jar
bioumlsim/jars/org.apache.commons.lang_2.4.0.jar
bioumlsim/jars/org.apache.velocity_1.6.2.jar
bioumlsim/jars/org.json-20170516.jar
bioumlsim/jars/ru.biosoft.access_0.9.10.jar
bioumlsim/jars/ru.biosoft.exception-1.0.0.jar
bioumlsim/jars/ru.biosoft.graph_0.9.10.jar
bioumlsim/jars/ru.biosoft.graphics_0.9.10.jar
bioumlsim/jars/ru.biosoft.jobcontrol-2.0.0.jar
bioumlsim/jars/ru.biosoft.math_0.9.10.jar
bioumlsim/jars/src.jar
bioumlsim/jars/streamex-0.7.0.jar
bioumlsim-0.6.3.dist-info/LICENSE
bioumlsim-0.6.3.dist-info/METADATA
bioumlsim-0.6.3.dist-info/WHEEL
bioumlsim-0.6.3.dist-info/top_level.txt
bioumlsim-0.6.3.dist-info/RECORD
