Metadata-Version: 2.1
Name: bioumlsim
Version: 0.6.3
Summary: Python interface for simulation with BioUML
Home-page: https://www.biouml.org/
Author: Ilya Kiselev, Biosoft.ru
Author-email: 4x3cut0r@gmail.com
Project-URL: Bug Tracker, https://github.com/Biosoft-ru/bioumlsim/issues
Project-URL: Source Code, https://github.com/Biosoft-ru/bioumlsim
Classifier: Programming Language :: Python :: 3
Classifier: Programming Language :: Python :: 3 :: Only
Classifier: License :: OSI Approved :: MIT License
Classifier: Operating System :: OS Independent
Classifier: Topic :: Scientific/Engineering :: Mathematics
Requires-Python: >=3.6
License-File: LICENSE
Requires-Dist: jpype1
Requires-Dist: numpy
Requires-Dist: pandas
Requires-Dist: matplotlib
Requires-Dist: install-jdk
